{
  "kernel_name": "chunk_gated_delta_rule_fwd_kernel_h_blockdim64",
  "triton_version": "3.4.0",
  "default_config": {
    "kwargs": {
      "BV": 32
    },
    "num_warps": 4,
    "num_ctas": 1,
    "num_stages": 3
  },
  "autotune_entries": {
    "51ff639fdab664eed7d3f4a4c04ae0f3": {
      "autotune_key": [
        4,
        100,
        100,
        64,
        "torch.float16",
        "torch.float16",
        "torch.float16",
        "torch.float16",
        "torch.float32",
        "torch.float16",
        "torch.float32",
        "torch.float32"
      ],
      "config": {
        "kwargs": {
          "BV": 32
        },
        "num_warps": 4,
        "num_ctas": 1,
        "num_stages": 3,
        "maxnreg": null,
        "pre_hook": null,
        "ir_override": null
      },
      "best_timing": [
        0.052928000688552856,
        0.0525440014898777,
        0.0533440001308918
      ]
    },
    "96eabe58eeec1a9e6a122111e63adf40": {
      "autotune_key": [
        4,
        100,
        100,
        64,
        "torch.float16",
        "torch.float16",
        "torch.float16",
        "torch.float16",
        "torch.float32",
        "torch.float16",
        "torch.float32"
      ],
      "config": {
        "kwargs": {
          "BV": 32
        },
        "num_warps": 4,
        "num_ctas": 1,
        "num_stages": 3,
        "maxnreg": null,
        "pre_hook": null,
        "ir_override": null
      },
      "best_timing": [
        0.05244800075888634,
        0.05212799832224846,
        0.05286400020122528
      ]
    }
  }
}